{"title":"Alcohol 120% v.1.9.7.  Build 6022","uid":4056594,"size":10571567,"categoryP":"applications","categoryS":"windows","magnet":"?xt=urn:btih:011d77b1a9a0372c7c13d2dc4978b5d0b83c1315&amp;dn=Alcohol+120%25+v.1.9.7.++Build+6022&amp;tr=udp%3A%2F%2Ftracker.openbittorrent.com%3A80&amp;tr=udp%3A%2F%2Fopen.demonii.com%3A1337&amp;tr=udp%3A%2F%2Ftracker.coppersurfer.tk%3A6969&amp;tr=udp%3A%2F%2Fexodus.desync.com%3A6969","seeders":0,"leechers":0,"uploader":"Tiberius360","files":5,"time":1204397179,"description":"Alcohol 120% w/ working Crack","torrent":{"xt":"urn:btih:011d77b1a9a0372c7c13d2dc4978b5d0b83c1315","amp;dn":"Alcohol+120%25+v.1.9.7.++Build+6022","amp;tr":["udp%3A%2F%2Ftracker.openbittorrent.com%3A80","udp%3A%2F%2Fopen.demonii.com%3A1337","udp%3A%2F%2Ftracker.coppersurfer.tk%3A6969","udp%3A%2F%2Fexodus.desync.com%3A6969"],"infoHash":"011d77b1a9a0372c7c13d2dc4978b5d0b83c1315","infoHashBuffer":{"type":"Buffer","data":[1,29,119,177,169,160,55,44,124,19,210,220,73,120,181,208,184,60,19,21]},"announce":[],"urlList":[]}}