{"title":"Reflections from Broadway","uid":4159315,"size":58896682,"categoryP":"audio","categoryS":"music","magnet":"?xt=urn:btih:0842d6f0a9b64f2aaa4535a525097cd4c12357b7&amp;dn=Reflections+from+Broadway&amp;tr=udp%3A%2F%2Ftracker.openbittorrent.com%3A80&amp;tr=udp%3A%2F%2Fopen.demonii.com%3A1337&amp;tr=udp%3A%2F%2Ftracker.coppersurfer.tk%3A6969&amp;tr=udp%3A%2F%2Fexodus.desync.com%3A6969","seeders":0,"leechers":1,"uploader":"dartsfan","files":18,"time":1209302334,"description":"John Barrowman, star of TV and stage, fantastic singing, great technique for singing students to emulate.  If you like it BUY it on Amazon.","torrent":{"xt":"urn:btih:0842d6f0a9b64f2aaa4535a525097cd4c12357b7","amp;dn":"Reflections+from+Broadway","amp;tr":["udp%3A%2F%2Ftracker.openbittorrent.com%3A80","udp%3A%2F%2Fopen.demonii.com%3A1337","udp%3A%2F%2Ftracker.coppersurfer.tk%3A6969","udp%3A%2F%2Fexodus.desync.com%3A6969"],"infoHash":"0842d6f0a9b64f2aaa4535a525097cd4c12357b7","infoHashBuffer":{"type":"Buffer","data":[8,66,214,240,169,182,79,42,170,69,53,165,37,9,124,212,193,35,87,183]},"announce":[],"urlList":[]}}