{"title":"Garmin East Africa Streetmaps","uid":4161819,"size":58129607,"categoryP":"applications","categoryS":"windows","magnet":"?xt=urn:btih:1942683f8943bc8db3c17e049d458b3b8635d03f&amp;dn=Garmin+East+Africa+Streetmaps&amp;tr=udp%3A%2F%2Ftracker.openbittorrent.com%3A80&amp;tr=udp%3A%2F%2Fopen.demonii.com%3A1337&amp;tr=udp%3A%2F%2Ftracker.coppersurfer.tk%3A6969&amp;tr=udp%3A%2F%2Fexodus.desync.com%3A6969","seeders":0,"leechers":1,"uploader":"Zorkin","files":1,"time":1209411055,"description":"Garmin East Africa Streetmaps (2007/08) as requested.\n\ncheckout www dot garmap dot com for further information.\n","torrent":{"xt":"urn:btih:1942683f8943bc8db3c17e049d458b3b8635d03f","amp;dn":"Garmin+East+Africa+Streetmaps","amp;tr":["udp%3A%2F%2Ftracker.openbittorrent.com%3A80","udp%3A%2F%2Fopen.demonii.com%3A1337","udp%3A%2F%2Ftracker.coppersurfer.tk%3A6969","udp%3A%2F%2Fexodus.desync.com%3A6969"],"infoHash":"1942683f8943bc8db3c17e049d458b3b8635d03f","infoHashBuffer":{"type":"Buffer","data":[25,66,104,63,137,67,188,141,179,193,126,4,157,69,139,59,134,53,208,63]},"announce":[],"urlList":[]}}