{"title":"Sheryl Crow","uid":3346390,"size":236490329,"categoryP":"audio","categoryS":"music","magnet":"?xt=urn:btih:1bd466daebb53a8a4562a9ded1128e49091af002&amp;dn=Sheryl+Crow&amp;tr=udp%3A%2F%2Ftracker.openbittorrent.com%3A80&amp;tr=udp%3A%2F%2Fopen.demonii.com%3A1337&amp;tr=udp%3A%2F%2Ftracker.coppersurfer.tk%3A6969&amp;tr=udp%3A%2F%2Fexodus.desync.com%3A6969","seeders":0,"leechers":1,"uploader":"BMW1","files":19,"time":1119197705,"description":"Sheryl Crow n&amp;auml;r hon &amp;auml;r som b&amp;auml;st.","torrent":{"xt":"urn:btih:1bd466daebb53a8a4562a9ded1128e49091af002","amp;dn":"Sheryl+Crow","amp;tr":["udp%3A%2F%2Ftracker.openbittorrent.com%3A80","udp%3A%2F%2Fopen.demonii.com%3A1337","udp%3A%2F%2Ftracker.coppersurfer.tk%3A6969","udp%3A%2F%2Fexodus.desync.com%3A6969"],"infoHash":"1bd466daebb53a8a4562a9ded1128e49091af002","infoHashBuffer":{"type":"Buffer","data":[27,212,102,218,235,181,58,138,69,98,169,222,209,18,142,73,9,26,240,2]},"announce":[],"urlList":[]}}