{"title":"The.Waterboy.1CD.1998.Soundtrack.[WmC]","uid":3223035,"size":66483790,"categoryP":"audio","categoryS":"music","magnet":"?xt=urn:btih:22d969de5e1a8e5748bec75771c91efe3b18e96c&amp;dn=The.Waterboy.1CD.1998.Soundtrack.%5BWmC%5D&amp;tr=udp%3A%2F%2Ftracker.openbittorrent.com%3A80&amp;tr=udp%3A%2F%2Fopen.demonii.com%3A1337&amp;tr=udp%3A%2F%2Ftracker.coppersurfer.tk%3A6969&amp;tr=udp%3A%2F%2Fexodus.desync.com%3A6969","seeders":0,"leechers":1,"uploader":"WmC-PL","files":19,"time":1089188013,"description":"-------------------------------------------------------------------\n                      The Waterboy OST\n-------------------------------------------------------------------\n\nAlbum................: The Waterboy OST\nYear.................: 1998\nCodec................: FhG\nVersion..............: MPEG 1 Layer III\nQuality..............: CBR 160, (avg. bitrate: 160kbps)\nChannels.............: Joint Stereo / 44100 hz\nID3-Tag v2...........: 2.3\n\nPosted by............: WmC\n\nIncluded.............: NFO, MD5, M3U\nCovers...............: Front Back \n\n-------------------------------------------------------------------\n                       Tracklisting\n-------------------------------------------------------------------\n\n01. (05:14) - (CBR 160 kbit/s) Creedence Clearwater Revival - Born On The Bayou\n02. (03:22) - (CBR 160 kbit/s) Goldfinger - More Today Than Yesterday\n03. (03:33) - (CBR 160 kbit/s) Big Head Todd &amp;amp; The Monsters - Boom Boom\n04. (03:35) - (CBR 160 kbit/s) The Candyskins - Feed It\n05. (02:57) - (CBR 160 kbit/s) Peace Frogs - The Doors\n06. (05:37) - (CBR 160 kbit/s) Earth, Wind &amp;amp; Fire - Let's Groove\n07. (03:52) - (CBR 160 kbit/s) Lenny Kravitz - Always On The Run\n08. (04:09) - (CBR 160 kbit/s) Lifelong featuring Incident - Doin' My Thang\n09. (03:40) - (CBR 160 kbit/s) John Mellencamp - Small Town\n10. (04:00) - (CBR 160 kbit/s) Joe Walsh - New Years Eve\n11. (05:58) - (CBR 160 kbit/s) Allman Brothers - No One To Run With\n12. (04:34) - (CBR 160 kbit/s) Rush - Tom Sawyer\n13. (04:17) - (CBR 160 kbit/s) Candlebox - Glowing Soul\n\nPlaying Time.........: 54:56\nTotal Size...........: 62,89 MB\n\n-------------------------------------------------------------------\nbrought by WarezmastersCrew\n-------------------------------------------------------------------","torrent":{"xt":"urn:btih:22d969de5e1a8e5748bec75771c91efe3b18e96c","amp;dn":"The.Waterboy.1CD.1998.Soundtrack.%5BWmC%5D","amp;tr":["udp%3A%2F%2Ftracker.openbittorrent.com%3A80","udp%3A%2F%2Fopen.demonii.com%3A1337","udp%3A%2F%2Ftracker.coppersurfer.tk%3A6969","udp%3A%2F%2Fexodus.desync.com%3A6969"],"infoHash":"22d969de5e1a8e5748bec75771c91efe3b18e96c","infoHashBuffer":{"type":"Buffer","data":[34,217,105,222,94,26,142,87,72,190,199,87,113,201,30,254,59,24,233,108]},"announce":[],"urlList":[]}}