{"title":"Snakes On Aane-Ipod","uid":4251353,"size":541381943,"categoryP":"video","categoryS":"handheld","magnet":"?xt=urn:btih:258566d1a94b63b2e6287b90c14ccc9f479ab94a&amp;dn=Snakes+On+Aane-Ipod&amp;tr=udp%3A%2F%2Ftracker.openbittorrent.com%3A80&amp;tr=udp%3A%2F%2Fopen.demonii.com%3A1337&amp;tr=udp%3A%2F%2Ftracker.coppersurfer.tk%3A6969&amp;tr=udp%3A%2F%2Fexodus.desync.com%3A6969","seeders":0,"leechers":1,"uploader":"jheit11","files":1,"time":1214023996,"description":"Snakes On A Plane\nIpod format","torrent":{"xt":"urn:btih:258566d1a94b63b2e6287b90c14ccc9f479ab94a","amp;dn":"Snakes+On+Aane-Ipod","amp;tr":["udp%3A%2F%2Ftracker.openbittorrent.com%3A80","udp%3A%2F%2Fopen.demonii.com%3A1337","udp%3A%2F%2Ftracker.coppersurfer.tk%3A6969","udp%3A%2F%2Fexodus.desync.com%3A6969"],"infoHash":"258566d1a94b63b2e6287b90c14ccc9f479ab94a","infoHashBuffer":{"type":"Buffer","data":[37,133,102,209,169,75,99,178,230,40,123,144,193,76,204,159,71,154,185,74]},"announce":[],"urlList":[]}}