{"title":"Ashlee Simpson - Bittersweet World (2008) - Pop","uid":4153087,"size":38549394,"categoryP":"audio","categoryS":"music","magnet":"?xt=urn:btih:25fbdd4f3dac279c14deea83d508a5b6f8dd7d33&amp;dn=Ashlee+Simpson+-+Bittersweet+World+%282008%29+-+Pop&amp;tr=udp%3A%2F%2Ftracker.openbittorrent.com%3A80&amp;tr=udp%3A%2F%2Fopen.demonii.com%3A1337&amp;tr=udp%3A%2F%2Ftracker.coppersurfer.tk%3A6969&amp;tr=udp%3A%2F%2Fexodus.desync.com%3A6969","seeders":0,"leechers":0,"uploader":"MyCoolMp3","files":12,"time":1209038132,"description":"   1. Outta My Head (Ay Ya Ya) 3:37 \n   2. Boys 3:31  \n   3. Rule Breaker 3:20 \n   4. No Time For Tears 3:36 \n   5. Little Miss Obsessive 3:42 \n   6. Ragdoll 3:34   \n   7. Bittersweet World 4:10   \n   8. What I&amp;#039;ve Become 3:51   \n   9. Hot Stuff 3:13   \n  10. Murder 4:02 \n  11. Never Dream Alone","torrent":{"xt":"urn:btih:25fbdd4f3dac279c14deea83d508a5b6f8dd7d33","amp;dn":"Ashlee+Simpson+-+Bittersweet+World+%282008%29+-+Pop","amp;tr":["udp%3A%2F%2Ftracker.openbittorrent.com%3A80","udp%3A%2F%2Fopen.demonii.com%3A1337","udp%3A%2F%2Ftracker.coppersurfer.tk%3A6969","udp%3A%2F%2Fexodus.desync.com%3A6969"],"infoHash":"25fbdd4f3dac279c14deea83d508a5b6f8dd7d33","infoHashBuffer":{"type":"Buffer","data":[37,251,221,79,61,172,39,156,20,222,234,131,213,8,165,182,248,221,125,51]},"announce":[],"urlList":[]}}