{"title":"Desperado.1995.PAL","uid":3341732,"size":6306083367,"categoryP":"video","categoryS":"movies_dvdr","magnet":"?xt=urn:btih:415241e0b53373f8900b43c5b203e482d9c7ad53&amp;dn=Desperado.1995.PAL&amp;tr=udp%3A%2F%2Ftracker.openbittorrent.com%3A80&amp;tr=udp%3A%2F%2Fopen.demonii.com%3A1337&amp;tr=udp%3A%2F%2Ftracker.coppersurfer.tk%3A6969&amp;tr=udp%3A%2F%2Fexodus.desync.com%3A6969","seeders":0,"leechers":0,"uploader":"ubbe1000","files":3,"time":1118240240,"description":"\n    |----------------------------------------------------------------------|\n    |----------------------------------------------------------------------|                                                              \n    |  MovieName......: Desperado                  \n    |  Packager.......:                                           \n    |  Retail Date....: 2003                                   \n    |  Release Date...: 1995                                        \n    |  Source.........: DVD Retail                                       \n    |  Genre..........: Action                             \n    |  Type...........: DVD-R                                         \n    |  Format.........: .iso\n    |  Rars...........:                                                                                        \n    |  Playtime.......: 106 min                                            \n    |  IMDB...........: 6.8/10 (18,243 votes) http://imdb.com/title/tt0112851/                            \n    |        \n    |----------------------------------------------------------------------|  \n    |----------------------------------------------------------------------|\n    |  ASPECT &amp; STANDARD     |   AUDIO                                     |\n    |                        |                                             | \n    |  [ ] Widescreen        |   [X] English    [X] Dolby Digital 5.1      | \n    |  [X] Anamorphic        |   [ ] Danish     [ ] DTS 6.1                | \n    |  [ ] Letterbox         |   [ ] Norwegian  [ ] Dolby Sorround 2.0     | \n    |  [ ] Fullscreen        |   [ ] Swedish    [ ] Dolby Digital 2.0      |\n    |  [X] PAL   [ ] NTSC    |   [ ] Finnish    [ ] Directory Commentary   |\n    |                        |   [X] Hungarian  [ ] Stereo                 |\n    |----------------------------------------------------------------------|\n    |----------------------------------------------------------------------| \n    |  SUBTITLES                                                           |\n    |                                                                      |\n    |  [X] English       [X] Arabic       [X] Spanish       [X] Dutch      |\n    |  [X] Swedish       [ ] German       [X] Polish        [X] Italia     |\n    |  [X] Danish        [X] Bulgarian    [X] Czech         [X] Greek      |\n    |  [X] Norwegian     [ ] Hrvatski     [X] Magyar        [ ] Russian    |\n    |  [X] Suomi         [X] Turkish      [X] Icelandic     [X] Slove      |\n    |  [X] Hindi         [ ] French       [X] Hebrew        [X] Others     |\n    |                                                                      |\n    |----------------------------------------------------------------------|\n    |----------------------------------------------------------------------|\n    |  VIDEO               |  MENU                 |  DVD-EXTRAS           |\n    |                      |                       |                       |\n    |  [X] Untouched       |  [X] Untouched        |  [X] Untouched        |\n    |  [ ] Re-Encoded      |  [ ] Stripped         |  [ ] Stripped         |     \n    |  Passes  [ ]         |  [ ] Partial Stripped |  [ ] Partial Stripped |\n    |  Bitrate [   ]       |                       |  [ ] Re-Encoded       |\n    |----------------------------------------------------------------------|\n    |----------------------------------------------------------------------|\n     \n     PLOT OUTLINE:\n     \n     Sharp knives, big guns, awesome fights, great dialogue, wonderful\n     characters and Selma Hayek looks better then ever. These are just a\n     few reasons why I like this movie.\n\n     &quot;Desperado&quot; is more than an action movie. It has tons of fun in it\n     which makes the movie extremely likeable to watch. The action is way\n     over the top but it works very well since the movie obviously doesn't\n     take itself serious. It's fun and cool to watch at the same time.\n\n     &quot;Desperado&quot; is a kind of movie that really needs no story and basicily\n     there isn't really any. All the fun characters, dialogue and action\n     sequences make you forget that there isn't really a story.\n     The Quentin Tarantino cameo is especially entertaining and so are almost\n     every Mexican bad guy that are all in one way or another over the top.\n                   \n","torrent":{"xt":"urn:btih:415241e0b53373f8900b43c5b203e482d9c7ad53","amp;dn":"Desperado.1995.PAL","amp;tr":["udp%3A%2F%2Ftracker.openbittorrent.com%3A80","udp%3A%2F%2Fopen.demonii.com%3A1337","udp%3A%2F%2Ftracker.coppersurfer.tk%3A6969","udp%3A%2F%2Fexodus.desync.com%3A6969"],"infoHash":"415241e0b53373f8900b43c5b203e482d9c7ad53","infoHashBuffer":{"type":"Buffer","data":[65,82,65,224,181,51,115,248,144,11,67,197,178,3,228,130,217,199,173,83]},"announce":[],"urlList":[]}}