{"title":"Madonna feat Justin Timberlake -4 MINUTES - (NEW SINGLE!!!) ","uid":4055353,"size":46794629,"categoryP":"audio","categoryS":"music","magnet":"?xt=urn:btih:42da91774e661a9bba9472da53c87892be3f8dd7&amp;dn=Madonna+feat+Justin+Timberlake+-4+MINUTES+-+%28NEW+SINGLE%21%21%21%29+&amp;tr=udp%3A%2F%2Ftracker.openbittorrent.com%3A80&amp;tr=udp%3A%2F%2Fopen.demonii.com%3A1337&amp;tr=udp%3A%2F%2Ftracker.coppersurfer.tk%3A6969&amp;tr=udp%3A%2F%2Fexodus.desync.com%3A6969","seeders":0,"leechers":2,"uploader":"DefyingGravity","files":3,"time":1204341511,"description":"First new single from Madonna&amp;#039;s new album HARD CANDY ! Was aired on french radio FG ! (+ RAIN/EROTICA TAPES PROMO because it was not possible to only upload one song..) ENJOY","torrent":{"xt":"urn:btih:42da91774e661a9bba9472da53c87892be3f8dd7","amp;dn":"Madonna+feat+Justin+Timberlake+-4+MINUTES+-+%28NEW+SINGLE%21%21%21%29+","amp;tr":["udp%3A%2F%2Ftracker.openbittorrent.com%3A80","udp%3A%2F%2Fopen.demonii.com%3A1337","udp%3A%2F%2Ftracker.coppersurfer.tk%3A6969","udp%3A%2F%2Fexodus.desync.com%3A6969"],"infoHash":"42da91774e661a9bba9472da53c87892be3f8dd7","infoHashBuffer":{"type":"Buffer","data":[66,218,145,119,78,102,26,155,186,148,114,218,83,200,120,146,190,63,141,215]},"announce":[],"urlList":[]}}