{"title":"Blacklist - EPs [2007/MP3/192]","uid":4265619,"size":41817237,"categoryP":"audio","categoryS":"music","magnet":"?xt=urn:btih:472501b9011f55dd2f34455eb1605de0423db69c&amp;dn=Blacklist+-+EPs+%5B2007%2FMP3%2F192%5D&amp;tr=udp%3A%2F%2Ftracker.openbittorrent.com%3A80&amp;tr=udp%3A%2F%2Fopen.demonii.com%3A1337&amp;tr=udp%3A%2F%2Ftracker.coppersurfer.tk%3A6969&amp;tr=udp%3A%2F%2Fexodus.desync.com%3A6969","seeders":0,"leechers":1,"uploader":"my_heroine","files":6,"time":1214679581,"description":"Blacklist EP (2005)\nself-released\n\n1. Language of the Living Dead \n2. Exit \n3. Dawn of the Idols\n-------------------------------\nSolidaire EP (2007)\nWierd Records, VR-002\n\n1. Blue Shifted \n2. Shock In The Hotel Falcon\n3. Pure Joy In My Heart\n  \t\n\nRIYL : The Chameleons, U2, Interpol, Bauhaus, The Cure, Muse, The Cult, Placebo, Sisters of Mercy\n\t\n\n","torrent":{"xt":"urn:btih:472501b9011f55dd2f34455eb1605de0423db69c","amp;dn":"Blacklist+-+EPs+%5B2007%2FMP3%2F192%5D","amp;tr":["udp%3A%2F%2Ftracker.openbittorrent.com%3A80","udp%3A%2F%2Fopen.demonii.com%3A1337","udp%3A%2F%2Ftracker.coppersurfer.tk%3A6969","udp%3A%2F%2Fexodus.desync.com%3A6969"],"infoHash":"472501b9011f55dd2f34455eb1605de0423db69c","infoHashBuffer":{"type":"Buffer","data":[71,37,1,185,1,31,85,221,47,52,69,94,177,96,93,224,66,61,182,156]},"announce":[],"urlList":[]}}