{"title":"Britney Spears-Blackout [2007][CD+SkidVid_XviD+Cov]192Kbps","uid":4060121,"size":109312479,"categoryP":"audio","categoryS":"music","magnet":"?xt=urn:btih:66a96fff2c5110a5c43a53c73da28b99387a8fd5&amp;dn=Britney+Spears-Blackout+%5B2007%5D%5BCD%2BSkidVid_XviD%2BCov%5D192Kbps&amp;tr=udp%3A%2F%2Ftracker.openbittorrent.com%3A80&amp;tr=udp%3A%2F%2Fopen.demonii.com%3A1337&amp;tr=udp%3A%2F%2Ftracker.coppersurfer.tk%3A6969&amp;tr=udp%3A%2F%2Fexodus.desync.com%3A6969","seeders":0,"leechers":0,"uploader":"dgmmanagement","files":17,"time":1204573224,"description":"Britney Spears Blackout","torrent":{"xt":"urn:btih:66a96fff2c5110a5c43a53c73da28b99387a8fd5","amp;dn":"Britney+Spears-Blackout+%5B2007%5D%5BCD%2BSkidVid_XviD%2BCov%5D192Kbps","amp;tr":["udp%3A%2F%2Ftracker.openbittorrent.com%3A80","udp%3A%2F%2Fopen.demonii.com%3A1337","udp%3A%2F%2Ftracker.coppersurfer.tk%3A6969","udp%3A%2F%2Fexodus.desync.com%3A6969"],"infoHash":"66a96fff2c5110a5c43a53c73da28b99387a8fd5","infoHashBuffer":{"type":"Buffer","data":[102,169,111,255,44,81,16,165,196,58,83,199,61,162,139,153,56,122,143,213]},"announce":[],"urlList":[]}}