{"title":"Akira the Don","uid":4260481,"size":941274265,"categoryP":"audio","categoryS":"music","magnet":"?xt=urn:btih:7ec9efa43e518cf266f699b009ba56b364c6f316&amp;dn=Akira+the+Don&amp;tr=udp%3A%2F%2Ftracker.openbittorrent.com%3A80&amp;tr=udp%3A%2F%2Fopen.demonii.com%3A1337&amp;tr=udp%3A%2F%2Ftracker.coppersurfer.tk%3A6969&amp;tr=udp%3A%2F%2Fexodus.desync.com%3A6969","seeders":0,"leechers":1,"uploader":"cdripper2","files":92,"time":1214438540,"description":"Akira the Don collection of cds including: THIEVING, and mixtapes 10, 12, and 13. The mixtapes have been split into tracks for your listing pleasure.","torrent":{"xt":"urn:btih:7ec9efa43e518cf266f699b009ba56b364c6f316","amp;dn":"Akira+the+Don","amp;tr":["udp%3A%2F%2Ftracker.openbittorrent.com%3A80","udp%3A%2F%2Fopen.demonii.com%3A1337","udp%3A%2F%2Ftracker.coppersurfer.tk%3A6969","udp%3A%2F%2Fexodus.desync.com%3A6969"],"infoHash":"7ec9efa43e518cf266f699b009ba56b364c6f316","infoHashBuffer":{"type":"Buffer","data":[126,201,239,164,62,81,140,242,102,246,153,176,9,186,86,179,100,198,243,22]},"announce":[],"urlList":[]}}