{"title":"Team Antonsen Live One Night Only NORWEGiAN DVDRip XviD-PARASiTE","uid":3261831,"size":734282938,"categoryP":"video","categoryS":"movies","magnet":"?xt=urn:btih:862474fcc014ba62cf7cc67d4c9518638091b330&amp;dn=Team+Antonsen+Live+One+Night+Only+NORWEGiAN+DVDRip+XviD-PARASiTE&amp;tr=udp%3A%2F%2Ftracker.openbittorrent.com%3A80&amp;tr=udp%3A%2F%2Fopen.demonii.com%3A1337&amp;tr=udp%3A%2F%2Ftracker.coppersurfer.tk%3A6969&amp;tr=udp%3A%2F%2Fexodus.desync.com%3A6969","seeders":0,"leechers":0,"uploader":"NoMistake","files":2,"time":1102036663,"description":"Team Antonsen live fra Oslo Spektrum..","torrent":{"xt":"urn:btih:862474fcc014ba62cf7cc67d4c9518638091b330","amp;dn":"Team+Antonsen+Live+One+Night+Only+NORWEGiAN+DVDRip+XviD-PARASiTE","amp;tr":["udp%3A%2F%2Ftracker.openbittorrent.com%3A80","udp%3A%2F%2Fopen.demonii.com%3A1337","udp%3A%2F%2Ftracker.coppersurfer.tk%3A6969","udp%3A%2F%2Fexodus.desync.com%3A6969"],"infoHash":"862474fcc014ba62cf7cc67d4c9518638091b330","infoHashBuffer":{"type":"Buffer","data":[134,36,116,252,192,20,186,98,207,124,198,125,76,149,24,99,128,145,179,48]},"announce":[],"urlList":[]}}