{"title":"Viva La Muerte - Fernando Arrabal / DVDR","uid":4024009,"size":4465252614,"categoryP":"video","categoryS":"movies_dvdr","magnet":"?xt=urn:btih:97ec8da3a6bb84da13d8642ca66004563d69015b&amp;dn=Viva+La+Muerte+-+Fernando+Arrabal+%2F+DVDR&amp;tr=udp%3A%2F%2Ftracker.openbittorrent.com%3A80&amp;tr=udp%3A%2F%2Fopen.demonii.com%3A1337&amp;tr=udp%3A%2F%2Ftracker.coppersurfer.tk%3A6969&amp;tr=udp%3A%2F%2Fexodus.desync.com%3A6969","seeders":0,"leechers":1,"uploader":"mondo","files":2,"time":1202777973,"description":"Viva La Muerte - Fernando Arrabal - 1971 (CUlt Epics release)\nUncompressed DVD with all extras included.\n\nLanguage:\nFrench or Spanish\n\nSubtitles:\nEnglish\n\n\nExtras:\nInterview with Fernando Arrabal, Lobbycard gallery, Trailer.\n\nFernando ArrabalÃ‚Â´s surreal masterpiece\n\n&quot;At the end of the Spanish civil war, Fando, a boy of about ten, tries to make sense of war and his father&amp;#039;s arrest. His mother is religious, sympathetic to the Fascists; his father is accused of being a Red. Fando discovers that his mother may have aided in his father&amp;#039;s arrest. Sometimes we witness Fando imagining explanations for what&amp;#039;s going on; sometimes we see him at play, alone or with his friend ThÃƒÂ©rÃƒÂ¨se. Oedipal fantasies and a lad&amp;#039;s natural curiosity about sex and death mix with his search for his mother&amp;#039;s nature and his father&amp;#039;s fate. Will Fando survive the search?&quot;\n\nI also have &quot;The Guernica Tree&quot; and &quot;I Will Walk Like a Crazy Horse&quot; on DVD. Write a comment if you want them uploaded here.\n\nEnjoy!","torrent":{"xt":"urn:btih:97ec8da3a6bb84da13d8642ca66004563d69015b","amp;dn":"Viva+La+Muerte+-+Fernando+Arrabal+%2F+DVDR","amp;tr":["udp%3A%2F%2Ftracker.openbittorrent.com%3A80","udp%3A%2F%2Fopen.demonii.com%3A1337","udp%3A%2F%2Ftracker.coppersurfer.tk%3A6969","udp%3A%2F%2Fexodus.desync.com%3A6969"],"infoHash":"97ec8da3a6bb84da13d8642ca66004563d69015b","infoHashBuffer":{"type":"Buffer","data":[151,236,141,163,166,187,132,218,19,216,100,44,166,96,4,86,61,105,1,91]},"announce":[],"urlList":[]}}