{"title":"DVD TO MOBILE Nokia Edition v1 0 0 WinALL-CHiCNCREAM","uid":3254402,"size":3611270,"categoryP":"applications","categoryS":"windows","magnet":"?xt=urn:btih:a488c209fa3d98e026ae589c8b8b81881dd518cd&amp;dn=DVD+TO+MOBILE+Nokia+Edition+v1+0+0+WinALL-CHiCNCREAM&amp;tr=udp%3A%2F%2Ftracker.openbittorrent.com%3A80&amp;tr=udp%3A%2F%2Fopen.demonii.com%3A1337&amp;tr=udp%3A%2F%2Ftracker.coppersurfer.tk%3A6969&amp;tr=udp%3A%2F%2Fexodus.desync.com%3A6969","seeders":0,"leechers":0,"uploader":"BeMyGuest","files":3,"time":1100017927,"description":"Now you can convert your DVDs to your Nokia, Siemens and other            \n        brand mobile phone and watch them in great quality, with excellent          \n        sound and in full screen landscape mode*. A memorycard as small as          \n        128 Mb is sufficient to store a full length feature film, up to a          \n        hundred minutes. Take your DVDs on the plane, train or automobile,          \n       watch them on vacation, at work or at school. With only two clicks,         \n        this PC software converts the content of your DVD to a super small          \n        movie file, which will play on any Symbian Series 60 device, such          \n         as Nokia 6600/7610/6630/6260, Siemens SX-1, Sendo X, etc. on a            \n          postage stamp size memory card. You can use a headset or the             \n         built-in speaker to listen to the sound. Subtitled and foreign            \n        language DVDs are also supported. You wil have to see the quality          \n         to believe it, using supreme MPEG4 encoding, feature films look           \n            crisp and sharp on your cellular phone and still fit on a              \n                        relatively small multimediacard.                           \n                                                                                   \n                       The following phones are supported:                         \n                                                                                   \n       NOKIA 3620, 3650, 3660, 6260, 6600, 6620, 6630, 6670, 7610, N-Gage,         \n             QD SIEMENS SX-1, PANASONIC X700, SAMSUNG D710, SENDO X","torrent":{"xt":"urn:btih:a488c209fa3d98e026ae589c8b8b81881dd518cd","amp;dn":"DVD+TO+MOBILE+Nokia+Edition+v1+0+0+WinALL-CHiCNCREAM","amp;tr":["udp%3A%2F%2Ftracker.openbittorrent.com%3A80","udp%3A%2F%2Fopen.demonii.com%3A1337","udp%3A%2F%2Ftracker.coppersurfer.tk%3A6969","udp%3A%2F%2Fexodus.desync.com%3A6969"],"infoHash":"a488c209fa3d98e026ae589c8b8b81881dd518cd","infoHashBuffer":{"type":"Buffer","data":[164,136,194,9,250,61,152,224,38,174,88,156,139,139,129,136,29,213,24,205]},"announce":[],"urlList":[]}}