{"title":"Adam &amp; The Ants - Live in Italy Many Years Ago","uid":4060855,"size":48095460,"categoryP":"audio","categoryS":"music","magnet":"?xt=urn:btih:b0a8aa510ff39fe21f190a8caa7d5be674b5fcd8&amp;dn=Adam+%26+The+Ants+-+Live+in+Italy+Many+Years+Ago&amp;tr=udp%3A%2F%2Ftracker.openbittorrent.com%3A80&amp;tr=udp%3A%2F%2Fopen.demonii.com%3A1337&amp;tr=udp%3A%2F%2Ftracker.coppersurfer.tk%3A6969&amp;tr=udp%3A%2F%2Fexodus.desync.com%3A6969","seeders":0,"leechers":0,"uploader":"markymarkymark","files":1,"time":1204592725,"description":"Adam &amp; The Ants live in Italy - 1978 I think","torrent":{"xt":"urn:btih:b0a8aa510ff39fe21f190a8caa7d5be674b5fcd8","amp;dn":"Adam+%26+The+Ants+-+Live+in+Italy+Many+Years+Ago","amp;tr":["udp%3A%2F%2Ftracker.openbittorrent.com%3A80","udp%3A%2F%2Fopen.demonii.com%3A1337","udp%3A%2F%2Ftracker.coppersurfer.tk%3A6969","udp%3A%2F%2Fexodus.desync.com%3A6969"],"infoHash":"b0a8aa510ff39fe21f190a8caa7d5be674b5fcd8","infoHashBuffer":{"type":"Buffer","data":[176,168,170,81,15,243,159,226,31,25,10,140,170,125,91,230,116,181,252,216]},"announce":[],"urlList":[]}}