{"title":"GTA San Andreas tweak for fast cars.rar","uid":4145134,"size":14337,"categoryP":"games","categoryS":"pc","magnet":"?xt=urn:btih:b1fbb65c366f70f067b0ce4dc6a2cf8f708d06e2&amp;dn=GTA+San+Andreas+tweak+for+fast+cars.rar&amp;tr=udp%3A%2F%2Ftracker.openbittorrent.com%3A80&amp;tr=udp%3A%2F%2Fopen.demonii.com%3A1337&amp;tr=udp%3A%2F%2Ftracker.coppersurfer.tk%3A6969&amp;tr=udp%3A%2F%2Fexodus.desync.com%3A6969","seeders":0,"leechers":0,"uploader":"DarkxFantom","files":1,"time":1208651082,"description":"Brought to you by:\n\nDarkxFantom\n\n\n\n\nI did not create this file\n\nit is a file located in the program files folder\n\nI just modified it.\n\n\nfirst its a good idea to back up the handling file just in case...\njust copy it to \\&quot;my documents\\&quot; or something.\n\nThen just copy this file into \nC:\\\\Program Files\\\\Rockstar Games\\\\GTA San Andreas\\\\data\nor whatever your install directory is for San Andreas\n\n\nlocated in the handling file is directions that you can\nuse to modify it more. \nthere is ALOT of stuff you can do to not only modify the\ncars in GTA but alot of other stuff to!!!!!\n\n\nThis has not been fully tested so tweak it some more\nyourself and have fun...\n\n\n\n","torrent":{"xt":"urn:btih:b1fbb65c366f70f067b0ce4dc6a2cf8f708d06e2","amp;dn":"GTA+San+Andreas+tweak+for+fast+cars.rar","amp;tr":["udp%3A%2F%2Ftracker.openbittorrent.com%3A80","udp%3A%2F%2Fopen.demonii.com%3A1337","udp%3A%2F%2Ftracker.coppersurfer.tk%3A6969","udp%3A%2F%2Fexodus.desync.com%3A6969"],"infoHash":"b1fbb65c366f70f067b0ce4dc6a2cf8f708d06e2","infoHashBuffer":{"type":"Buffer","data":[177,251,182,92,54,111,112,240,103,176,206,77,198,162,207,143,112,141,6,226]},"announce":[],"urlList":[]}}