{"title":"Chalmers Nollning H-sektionen 07.","uid":4139901,"size":6479288654,"categoryP":"video","categoryS":"movie_clips","magnet":"?xt=urn:btih:c4626a93a691475feea824c06a5d437ec99c3beb&amp;dn=Chalmers+Nollning+H-sektionen+07.&amp;tr=udp%3A%2F%2Ftracker.openbittorrent.com%3A80&amp;tr=udp%3A%2F%2Fopen.demonii.com%3A1337&amp;tr=udp%3A%2F%2Ftracker.coppersurfer.tk%3A6969&amp;tr=udp%3A%2F%2Fexodus.desync.com%3A6969","seeders":0,"leechers":1,"uploader":"fluffdesu","files":10,"time":1208446263,"description":"Filmer frÃƒÂ¥n Chalmers Nollning pÃƒÂ¥ H-sektionen.\nFullstÃƒÂ¤ndigt oredigerat.\n","torrent":{"xt":"urn:btih:c4626a93a691475feea824c06a5d437ec99c3beb","amp;dn":"Chalmers+Nollning+H-sektionen+07.","amp;tr":["udp%3A%2F%2Ftracker.openbittorrent.com%3A80","udp%3A%2F%2Fopen.demonii.com%3A1337","udp%3A%2F%2Ftracker.coppersurfer.tk%3A6969","udp%3A%2F%2Fexodus.desync.com%3A6969"],"infoHash":"c4626a93a691475feea824c06a5d437ec99c3beb","infoHashBuffer":{"type":"Buffer","data":[196,98,106,147,166,145,71,95,238,168,36,192,106,93,67,126,201,156,59,235]},"announce":[],"urlList":[]}}