{"title":"Vaginal Cumshots - Violet.mpg","uid":3253942,"size":18023918,"categoryP":"porn","categoryS":"movie_clips","magnet":"?xt=urn:btih:cc12eccb05d5a787db47e02964eb6e9054e9c842&amp;dn=Vaginal+Cumshots+-+Violet.mpg&amp;tr=udp%3A%2F%2Ftracker.openbittorrent.com%3A80&amp;tr=udp%3A%2F%2Fopen.demonii.com%3A1337&amp;tr=udp%3A%2F%2Ftracker.coppersurfer.tk%3A6969&amp;tr=udp%3A%2F%2Fexodus.desync.com%3A6969","seeders":0,"leechers":1,"uploader":"Swordcoast","files":1,"time":1099782108,"description":"Poor violet gets creamed","torrent":{"xt":"urn:btih:cc12eccb05d5a787db47e02964eb6e9054e9c842","amp;dn":"Vaginal+Cumshots+-+Violet.mpg","amp;tr":["udp%3A%2F%2Ftracker.openbittorrent.com%3A80","udp%3A%2F%2Fopen.demonii.com%3A1337","udp%3A%2F%2Ftracker.coppersurfer.tk%3A6969","udp%3A%2F%2Fexodus.desync.com%3A6969"],"infoHash":"cc12eccb05d5a787db47e02964eb6e9054e9c842","infoHashBuffer":{"type":"Buffer","data":[204,18,236,203,5,213,167,135,219,71,224,41,100,235,110,144,84,233,200,66]},"announce":[],"urlList":[]}}