{"title":"8-Bit Theater Episodes 001-900","uid":4021559,"size":136036620,"categoryP":"other","categoryS":"comics","magnet":"?xt=urn:btih:d3b9bd9f0935f757f8d49ea54c9a6457c3ad97b6&amp;dn=8-Bit+Theater+Episodes+001-900&amp;tr=udp%3A%2F%2Ftracker.openbittorrent.com%3A80&amp;tr=udp%3A%2F%2Fopen.demonii.com%3A1337&amp;tr=udp%3A%2F%2Ftracker.coppersurfer.tk%3A6969&amp;tr=udp%3A%2F%2Fexodus.desync.com%3A6969","seeders":0,"leechers":0,"uploader":"2Slick2Stretch","files":9,"time":1202684890,"description":"Episodes 1 - 900 of the very kick-ass comic &quot;8-Bit Theater&quot; by Brian Clavinger.  These are broken up into 9 pdf files with 100 episodes in each.  Once #1000 comes out, keep an eye out for the compendium!\n\nAlso, check out the original site. &lt;a href=&quot; http://www.muklearpower.com/&quot; rel=&quot;nofollow&quot; target=&quot;_NEW&quot;&gt; http://www.muklearpower.com/&lt;/a&gt;","torrent":{"xt":"urn:btih:d3b9bd9f0935f757f8d49ea54c9a6457c3ad97b6","amp;dn":"8-Bit+Theater+Episodes+001-900","amp;tr":["udp%3A%2F%2Ftracker.openbittorrent.com%3A80","udp%3A%2F%2Fopen.demonii.com%3A1337","udp%3A%2F%2Ftracker.coppersurfer.tk%3A6969","udp%3A%2F%2Fexodus.desync.com%3A6969"],"infoHash":"d3b9bd9f0935f757f8d49ea54c9a6457c3ad97b6","infoHashBuffer":{"type":"Buffer","data":[211,185,189,159,9,53,247,87,248,212,158,165,76,154,100,87,195,173,151,182]},"announce":[],"urlList":[]}}