{"title":"Avril Lavigne - Let Go","uid":4109382,"size":72153285,"categoryP":"audio","categoryS":"music","magnet":"?xt=urn:btih:e90626c255555d88875c5237e58b1923364da8ab&amp;dn=Avril+Lavigne+-+Let+Go&amp;tr=udp%3A%2F%2Ftracker.openbittorrent.com%3A80&amp;tr=udp%3A%2F%2Fopen.demonii.com%3A1337&amp;tr=udp%3A%2F%2Ftracker.coppersurfer.tk%3A6969&amp;tr=udp%3A%2F%2Fexodus.desync.com%3A6969","seeders":0,"leechers":0,"uploader":"lamstraal","files":18,"time":1206979383,"description":"Avril Lavigne - Let Go\n\n01  Avril Lavigne - Losing Grip (3:53) \n02  Avril Lavigne - Complicated (4:05) \n03  Avril Lavigne - Sk8er Boi (3:24) \n04  Avril Lavigne - I&amp;#039;m With You (3:43) \n05  Avril Lavigne - Mobile (3:32) \n06  Avril Lavigne - Unwanted (3:41) \n07  Avril Lavigne - Tomorrow (3:49) \n08  Avril Lavigne - Anything But Ordinary (4:11) \n09  Avril Lavigne - Things I&amp;#039;ll Never Say (3:44) \n10  Avril Lavigne - My World (3:27) \n11  Avril Lavigne - Nobody&amp;#039;s Fool (3:58)  \n12  Avril Lavigne - Too Much To Ask (3:45) \n13  Avril Lavigne - Naked (3:29) ","torrent":{"xt":"urn:btih:e90626c255555d88875c5237e58b1923364da8ab","amp;dn":"Avril+Lavigne+-+Let+Go","amp;tr":["udp%3A%2F%2Ftracker.openbittorrent.com%3A80","udp%3A%2F%2Fopen.demonii.com%3A1337","udp%3A%2F%2Ftracker.coppersurfer.tk%3A6969","udp%3A%2F%2Fexodus.desync.com%3A6969"],"infoHash":"e90626c255555d88875c5237e58b1923364da8ab","infoHashBuffer":{"type":"Buffer","data":[233,6,38,194,85,85,93,136,135,92,82,55,229,139,25,35,54,77,168,171]},"announce":[],"urlList":[]}}