{"title":"The Mist 2007.AC3-WAF[KvCD]-={CANUS RG}{JiZZA}=-","uid":4243717,"size":850923915,"categoryP":"video","categoryS":"movies","magnet":"?xt=urn:btih:ffb624aa334224ba399e0d149160730103923327&amp;dn=The+Mist+2007.AC3-WAF%5BKvCD%5D-%3D%7BCANUS+RG%7D%7BJiZZA%7D%3D-&amp;tr=udp%3A%2F%2Ftracker.openbittorrent.com%3A80&amp;tr=udp%3A%2F%2Fopen.demonii.com%3A1337&amp;tr=udp%3A%2F%2Ftracker.coppersurfer.tk%3A6969&amp;tr=udp%3A%2F%2Fexodus.desync.com%3A6969","seeders":0,"leechers":0,"uploader":"jizzames69","files":4,"time":1213683081,"description":"[img]http://upload.wikimedia.org/wikipedia/en/a/a1/The_Mist_poster.jpg[/img]\n\nThe Mist 2007.AC3-WAF[KvCD]-={CANUS RG}{JiZZA}=-\n\nTitle: Stephen King&amp;#039;s The Mist\n \nPlot Synosis: A freak storm unleashes a species of blood-thirsty creatures on a small town, where a small band of\n citizens hole-up in a supermarket and fight for their lives. \n\nCredited cast:\t\n\t\n\tThomas Jane\t... \tDavid Drayton\n\n\tMarcia Gay Harden\t... \tMrs. Carmody\n\n\tLaurie Holden\t... \tAmanda Dumfries\n\n\tAndre Braugher\t... \tBrent Norton\n\t\n\tToby Jones\t... \tOllie Weeks\n\n\tWilliam Sadler\t... \tJim\n\n\tJeffrey DeMunn\t... \tDan Miller\n\n\tFrances Sternhagen\t... \tIrene Reppler\n\n\tNathan Gamble\t... \tBilly Drayton\n\n\tAlexa Davalos\t... \tSally\n\n\tChris Owen\t... \tNorm\n\n\tSam Witwer\t... \tPrivate Jessup\n\n\tRobert C. Treveiler\t... \tBud Brown (as Robert Treveiler)\n\n\tDavid Jensen\t... \tMyron\n\n\tMelissa Suzanne McBride\t... \tWoman With Kids at Home (as Melissa McBride)\n\t\n\n\nh**p://www.imdb.com/title/tt0884328/\nGenre: Horror\nUser Rating:7.5/10 (36,698 votes) \nCountry: USA\nMPAA RATING: R\n\nOriginal Source: \nRelease Date: 21 November 2007 (USA) \nChapters: Every 5 Minutes\nRuntime: 126 minutes\nVideo: MPEG1/NTSC/352x240/29.97fps\nAudio: 44.1kHz/128kbps/Stereo\nRes: 352x240 / 29.97 fps\nSize: 798Mb(Bin file)\n \n\n\nTracked by: UKB, The Pirate Bay\n\n\nCome Visit Us At Canuslounge.net. Fun and friendly site! FREE REGISTRATION and EVERYONE IS WELCOME!:) ENJOY!\n\n\n[img]http://www.ukb-kvcd.com/k-stats/ffb624aa334224ba399e0d149160730103923327.png[/img]\n","torrent":{"xt":"urn:btih:ffb624aa334224ba399e0d149160730103923327","amp;dn":"The+Mist+2007.AC3-WAF%5BKvCD%5D-%3D%7BCANUS+RG%7D%7BJiZZA%7D%3D-","amp;tr":["udp%3A%2F%2Ftracker.openbittorrent.com%3A80","udp%3A%2F%2Fopen.demonii.com%3A1337","udp%3A%2F%2Ftracker.coppersurfer.tk%3A6969","udp%3A%2F%2Fexodus.desync.com%3A6969"],"infoHash":"ffb624aa334224ba399e0d149160730103923327","infoHashBuffer":{"type":"Buffer","data":[255,182,36,170,51,66,36,186,57,158,13,20,145,96,115,1,3,146,51,39]},"announce":[],"urlList":[]}}